reactivenet/__init__.py
reactivenet/enums.py
reactivenet/net.py
reactive_net-0.3.5.dist-info/LICENSE
reactive_net-0.3.5.dist-info/METADATA
reactive_net-0.3.5.dist-info/WHEEL
reactive_net-0.3.5.dist-info/top_level.txt
reactive_net-0.3.5.dist-info/RECORD
