Metadata-Version: 2.1
Name: reactive-net
Version: 0.3.5
Summary: Networking library for reactive-tools
Home-page: https://github.com/AuthenticExecution/reactive-net
Author: Gianluca Scopelliti
Author-email: gianlu.1033@gmail.com
License: UNKNOWN
Platform: UNKNOWN
Classifier: Programming Language :: Python :: 3
Classifier: License :: OSI Approved :: MIT License
Classifier: Operating System :: POSIX :: Linux
Requires-Python: >=3.6
